koya_utilities/__init__.py
koya_utilities/koya_utilities.py
koya_utilities-0.0.18.dist-info/LICENSE
koya_utilities-0.0.18.dist-info/METADATA
koya_utilities-0.0.18.dist-info/WHEEL
koya_utilities-0.0.18.dist-info/top_level.txt
koya_utilities-0.0.18.dist-info/RECORD
