Metadata-Version: 2.1
Name: koya-utilities
Version: 0.0.18
Author: 
Author-email: 
License: MIT
Requires-Python: >=3.6
License-File: LICENSE
Requires-Dist: pandas
Requires-Dist: sqlalchemy
Requires-Dist: numpy
Requires-Dist: tqdm
Requires-Dist: bcpandas
Requires-Dist: gspread
Requires-Dist: df2gspread
Requires-Dist: ipytest
Requires-Dist: transformers
Requires-Dist: datasets
Requires-Dist: wandb
Requires-Dist: html2text
